jupyterlab_atp_extension/__init__.py
jupyterlab_atp_extension/_version.py
jupyterlab_atp_extension/handlers.py
jupyterlab_atp_extension/public/index.html
jupyterlab_atp_extension-1.0.3.data/data/etc/jupyter/jupyter_server_config.d/jupyterlab_atp_extension.json
jupyterlab_atp_extension-1.0.3.data/data/share/jupyter/labextensions/@jupyterlab-atp/extension/build_log.json
jupyterlab_atp_extension-1.0.3.data/data/share/jupyter/labextensions/@jupyterlab-atp/extension/package.json
jupyterlab_atp_extension-1.0.3.data/data/share/jupyter/labextensions/@jupyterlab-atp/extension/schemas/@jupyterlab-atp/extension/package.json.orig
jupyterlab_atp_extension-1.0.3.data/data/share/jupyter/labextensions/@jupyterlab-atp/extension/schemas/@jupyterlab-atp/extension/plugin.json
jupyterlab_atp_extension-1.0.3.data/data/share/jupyter/labextensions/@jupyterlab-atp/extension/static/lib_index_js.26fbcc1bfc119506bf7e.js
jupyterlab_atp_extension-1.0.3.data/data/share/jupyter/labextensions/@jupyterlab-atp/extension/static/lib_index_js.26fbcc1bfc119506bf7e.js.map
jupyterlab_atp_extension-1.0.3.data/data/share/jupyter/labextensions/@jupyterlab-atp/extension/static/remoteEntry.2f1c24dbdc54fe8ff8a1.js
jupyterlab_atp_extension-1.0.3.data/data/share/jupyter/labextensions/@jupyterlab-atp/extension/static/remoteEntry.2f1c24dbdc54fe8ff8a1.js.map
jupyterlab_atp_extension-1.0.3.data/data/share/jupyter/labextensions/@jupyterlab-atp/extension/static/style.js
jupyterlab_atp_extension-1.0.3.data/data/share/jupyter/labextensions/@jupyterlab-atp/extension/static/style_index_js.f67bef73d30c780105a3.js
jupyterlab_atp_extension-1.0.3.data/data/share/jupyter/labextensions/@jupyterlab-atp/extension/static/style_index_js.f67bef73d30c780105a3.js.map
jupyterlab_atp_extension-1.0.3.data/data/share/jupyter/labextensions/@jupyterlab-atp/extension/install.json
jupyterlab_atp_extension-1.0.3.dist-info/METADATA
jupyterlab_atp_extension-1.0.3.dist-info/WHEEL
jupyterlab_atp_extension-1.0.3.dist-info/RECORD
