Metadata-Version: 2.1
Name: jupyterlab_atp_extension
Version: 1.0.3
Summary: A minimal JupyterLab extension opening a main area widget.
Project-URL: Homepage, https://github.com/jupyterlab/extension-examples
Project-URL: Bug Tracker, https://github.com/jupyterlab/extension-examples/issues
Project-URL: Repository, https://github.com/jupyterlab/extension-examples.git
Author: Project Jupyter Contributors
License: BSD-3-Clause License
Classifier: Framework :: Jupyter
Classifier: Framework :: Jupyter :: JupyterLab
Classifier: Framework :: Jupyter :: JupyterLab :: 4
Classifier: Framework :: Jupyter :: JupyterLab :: Extensions
Classifier: Framework :: Jupyter :: JupyterLab :: Extensions :: Prebuilt
Classifier: License :: OSI Approved :: BSD License
Classifier: Programming Language :: Python
Classifier: Programming Language :: Python :: 3
Classifier: Programming Language :: Python :: 3.8
Classifier: Programming Language :: Python :: 3.9
Classifier: Programming Language :: Python :: 3.10
Classifier: Programming Language :: Python :: 3.11
Requires-Python: >=3.8
